{
    "done": false,
    "value": {
        "type": "Feature",
        "properties": {},
        "geometry": {
            "type": "Polygon",
            "coordinates": [
                [
                    [-13624793.952741494, 4532644.812523604],
                    [-13624915.734392272, 4532502.061846862],
                    [-13625119.779144907, 4532588.3574537095],
                    [-13625044.774552042, 4532801.273717325],
                    [-13624793.952741494, 4532644.812523604]
                ]
            ]
        }
    }
}